bna/__init__.py
bna/__main__.py
bna/cli.py
bna/constants.py
bna/crypto.py
bna/http.py
bna/utils.py
bna-5.1.0.dist-info/entry_points.txt
bna-5.1.0.dist-info/LICENSE
bna-5.1.0.dist-info/WHEEL
bna-5.1.0.dist-info/METADATA
bna-5.1.0.dist-info/RECORD
