Metadata-Version: 2.1
Name: bna
Version: 5.1.0
Summary: Blizzard Authenticator and OTP library in Python
Home-page: https://github.com/jleclanche/python-bna
License: MIT
Author: Jerome Leclanche
Author-email: jerome@leclan.ch
Requires-Python: >=3.7,<4.0
Classifier: Development Status :: 5 - Production/Stable
Classifier: Environment :: Console
Classifier: Intended Audience :: Developers
Classifier: Intended Audience :: End Users/Desktop
Classifier: License :: OSI Approved :: MIT License
Classifier: Programming Language :: Python :: 3
Classifier: Programming Language :: Python :: 3.7
Classifier: Programming Language :: Python :: 3.8
Classifier: Programming Language :: Python :: 3.9
Classifier: Programming Language :: Python :: 3.10
Classifier: Topic :: Security
Classifier: Topic :: Security :: Cryptography
Requires-Dist: click (>=8.0.3,<9.0.0)
Requires-Dist: pyotp (>=2.6.0,<3.0.0)
Project-URL: Repository, https://github.com/jleclanche/python-bna
